startgg/__init__.py
startgg/async_base_client.py
startgg/attendee_count.py
startgg/attendee_count_events.py
startgg/base_model.py
startgg/client.py
startgg/enums.py
startgg/event_entrants.py
startgg/event_sets.py
startgg/event_standings.py
startgg/event_standings_race_format.py
startgg/exceptions.py
startgg/gamer_tag.py
startgg/in_progress_results.py
startgg/in_progress_set.py
startgg/input_types.py
startgg/last_result.py
startgg/league_schedule.py
startgg/league_standings.py
startgg/phase_group_sets.py
startgg/phase_groups_by_phase.py
startgg/phase_seeds.py
startgg/phase_seeds_teams.py
startgg/phase_sets.py
startgg/pool_seeds.py
startgg/prefix_search_attendees.py
startgg/scalars.py
startgg/set.py
startgg/set_entrants.py
startgg/sets.py
startgg/sets_at_station.py
startgg/shop.py
startgg/stream_queue_on_tournament.py
startgg/tournaments_by_country.py
startgg/tournaments_by_owner.py
startgg/tournaments_by_proximity.py
startgg/tournaments_by_state.py
startgg/tournaments_by_videogame.py
startgg/tournaments_by_videogames.py
startgg/upcoming.py
startgg-0.0.0.dist-info/METADATA
startgg-0.0.0.dist-info/WHEEL
startgg-0.0.0.dist-info/RECORD
